[
  {
    "name": "Qiskit",
    "licenses": ["Apache 2.0"],
    "programmingLanguages": ["JavaScript", "Python"],
    "compilerInputLanguages": ["OpenQASM"],
    "compilerOutputLanguages": ["OpenQASM"],
    "compilerOptimizationStrategies": ["hardware-specific", "hardware-independent"],
    "knowledgeReuses": [],
    "activeDevelopment": true,
    "supportedQuantumCloudServices": ["IBM Quantum", "Alpine Quantum Technologies"],
    "localSimulator": true
  },
  {
    "name": "Strawberry Fields",
    "licenses": ["Apache 2.0"],
    "programmingLanguages": ["Python"],
    "compilerInputLanguages": [],
    "compilerOutputLanguages": ["Blackbird"],
    "compilerOptimizationStrategies": ["hardware-independent", "hardware-specific"],
    "knowledgeReuses": [],
    "activeDevelopment": true,
    "supportedQuantumCloudServices": ["Xanadu Cloud Platform"],
    "localSimulator": true
  },
  {
    "name": "XACC",
    "licenses": ["Eclipse Public License", "Eclipse Distribution License"],
    "programmingLanguages": ["C++"],
    "compilerInputLanguages": ["Quil", "OpenQASM"],
    "compilerOutputLanguages": ["XASM", "Quil", "OpenQASM"],
    "compilerOptimizationStrategies": ["hardware-independent", "hardware-specific"],
    "knowledgeReuses": [],
    "activeDevelopment": true,
    "supportedQuantumCloudServices": ["IBM Quantum", "Rigetti QCS", "D-Wave Leap"],
    "localSimulator": true
  },
  {
    "name": "Ocean",
    "licenses": ["Apache 2.0"],
    "programmingLanguages": ["Python"],
    "compilerInputLanguages": ["BQM"],
    "compilerOutputLanguages": ["BQM"],
    "compilerOptimizationStrategies": [],
    "knowledgeReuses": [],
    "activeDevelopment": true,
    "supportedQuantumCloudServices": ["D-Wave Leap"],
    "localSimulator": true
  },
  {
    "name": "Cirq",
    "licenses": ["Apache 2.0"],
    "programmingLanguages": ["Python"],
    "compilerInputLanguages": ["OpenQASM", "Quirk", "Cirq-JSON"],
    "compilerOutputLanguages": ["Cirq-JSON"],
    "compilerOptimizationStrategies": ["hardware-independent", "hardware-specific"],
    "knowledgeReuses": [],
    "activeDevelopment": true,
    "supportedQuantumCloudServices": ["Google Cloud", "Alpine Quantum Technologies", "Pasqal"],
    "localSimulator": true
  },
  {
    "name": "Forest",
    "licenses": ["Apache 2.0"],
    "programmingLanguages": ["Python"],
    "compilerInputLanguages": [],
    "compilerOutputLanguages": ["Quil"],
    "compilerOptimizationStrategies": ["hardware-specific", "hardware-independent"],
    "knowledgeReuses": [],
    "activeDevelopment": true,
    "supportedQuantumCloudServices": ["Rigetti QCS"],
    "localSimulator": true
  },
  {
    "name": "ProjectQ",
    "licenses": ["Apache 2.0"],
    "programmingLanguages": ["Python"],
    "compilerInputLanguages": [],
    "compilerOutputLanguages": ["OpenQASM"],
    "compilerOptimizationStrategies": ["hardware-specific", "hardware-independent"],
    "knowledgeReuses": [],
    "activeDevelopment": false,
    "supportedQuantumCloudServices": ["IBM Quantum", "AQT"],
    "localSimulator": true
  },
  {
    "name": "Liqui|>",
    "licenses": ["Microsoft Research (custom)"],
    "programmingLanguages": ["F#"],
    "compilerInputLanguages": [],
    "compilerOutputLanguages": [],
    "compilerOptimizationStrategies": ["hardware-specific", "hardware-independent"],
    "knowledgeReuses": [],
    "activeDevelopment": false,
    "supportedQuantumCloudServices": [],
    "localSimulator": true
  },
  {
    "name": "JADE",
    "licenses": ["N/A"],
    "programmingLanguages": ["C++"],
    "compilerInputLanguages": [],
    "compilerOutputLanguages": [],
    "compilerOptimizationStrategies": [],
    "knowledgeReuses": [],
    "activeDevelopment": false,
    "supportedQuantumCloudServices": [],
    "localSimulator": true
  },
  {
    "name": "pytket",
    "licenses": ["Non-commercial"],
    "programmingLanguages": ["Python"],
    "compilerInputLanguages": ["OpenQASM", "Quipper"],
    "compilerOutputLanguages": ["OpenQASM"],
    "compilerOptimizationStrategies": ["hardware-independent", "hardware-specific"],
    "knowledgeReuses": [],
    "activeDevelopment": true,
    "supportedQuantumCloudServices": ["IBM Quantum", "Alpine Quantum Technologies", "AWS Braket", "Google Cloud", "Honeywell Quantum Systems", "Rigetti QCS", "Azure Quantum"],
    "localSimulator": true
  },
  {
    "name": "Quantum Development Kit",
    "licenses": ["MIT"],
    "programmingLanguages": ["Q#"],
    "compilerInputLanguages": [],
    "compilerOutputLanguages": [],
    "compilerOptimizationStrategies": [],
    "knowledgeReuses": [],
    "activeDevelopment": true,
    "supportedQuantumCloudServices": ["Azure Quantum"],
    "localSimulator": true
  },
  {
    "name": "Amazon Braket Python SDK",
    "licenses": ["Apache 2.0"],
    "programmingLanguages": ["Python"],
    "compilerInputLanguages": [],
    "compilerOutputLanguages": [],
    "compilerOptimizationStrategies": [],
    "knowledgeReuses": [],
    "activeDevelopment": true,
    "supportedQuantumCloudServices": ["AWS Braket"],
    "localSimulator": true
  }
]
